{
  "type": "FeatureCollection",
  "features": [
    {
      "type": "Feature",
      "geometry": {
        "type": "Point",
        "coordinates": [
          12.34,
          45.45
        ]
      },
      "properties": {
        "the_geom": "POINT (12.34 45.45)",
        "field_1": "SL_06",
        "institute_code": "PP1",
        "institute": "CoV",
        "map_name": "Misericorda",
        "id": 14,
        "name": " Venezia_Misericordia",
        "nothing1": null,
        "nothing2": "",
        "parameters": [
          "sea_surface_height",
          "wave_significant_height"
        ]
      }
    },
    {
      "type": "Feature",
      "geometry": {
        "type": "Point",
        "coordinates": [
          12.51,
          45.31
        ]
      },
      "properties": {
        "the_geom": "POINT (12.51 45.31)",
        "field_1": "SL_13",
        "institute_code": "PP2",
        "institute": "ISMAR",
        "map_name": "VE-PTF",
        "id": null,
        "name": "",
        "nothing1": null,
        "nothing2": "",
        "parameters": [
          "sea_surface_height",
          "wind_direction",
          "wind_speed",
          "wave_significant_height",
          "sea_surface_pressure",
          "air_temperature",
          "sea_water_temperature",
          "relative_humidity",
          "precipitation"
        ]
      }
    }
  ]
}